{
  "build": {
    "beforeDevCommand": "yarn dev",
    "beforeBuildCommand": "yarn build",
    "devPath": "http://localhost:1420",
    "distDir": "../dist",
    "withGlobalTauri": false
  },
  "package": {
    "productName": "manhours-manager",
    "version": "0.1.1"
  },
  "tauri": {
    "allowlist": {
      "all": false,
      "fs": {
        "all": false,
        "readFile": true,
        "writeFile": true
      },
      "dialog": {
        "all": false,
        "open": true,
        "save": true
      }
    },
    "bundle": {
      "active": true,
      "category": "Utility",
      "copyright": "",
      "deb": {
        "depends": []
      },
      "externalBin": [],
      "icon": [
        "icons/32x32.png",
        "icons/128x128.png",
        "icons/128x128@2x.png",
        "icons/icon.icns",
        "icons/icon.ico"
      ],
      "identifier": "ManHoursManager",
      "longDescription": "",
      "macOS": {
        "entitlements": null,
        "exceptionDomain": "",
        "frameworks": [],
        "providerShortName": null,
        "signingIdentity": null
      },
      "resources": [],
      "shortDescription": "",
      "targets": "all",
      "windows": {
        "certificateThumbprint": null,
        "digestAlgorithm": "sha256",
        "timestampUrl": ""
      }
    },
    "security": {
      "csp": null
    },
    "updater": {
      "active": false
    },
    "windows": [
      {
        "fullscreen": false,
        "resizable": true,
        "title": "",
        "width": 1200,
        "height": 800
      }
    ]
  }
}
